tdfpy/__init__.py
tdfpy/constants.py
tdfpy/noise.py
tdfpy/pandas_tdf.py
tdfpy/py.typed
tdfpy/spectra.py
tdfpy/timsdata.dll
tdfpy/timsdata.py
tdfpy/libtimsdata.so
tdfpy-0.2.0.dist-info/METADATA
tdfpy-0.2.0.dist-info/WHEEL
tdfpy-0.2.0.dist-info/licenses/LICENSE
tdfpy-0.2.0.dist-info/RECORD
