Metadata-Version: 2.4
Name: tdfpy
Version: 0.2.0
Summary: Python package for parsing Bruker timsTOF data with centroiding and noise filtering
Author-email: Patrick Garrett <pgarrett@scripps.edu>
License: MIT License
License-File: LICENSE
Keywords: bruker,mass-spectrometry,proteomics,tdf,timstof
Classifier: Development Status :: 4 - Beta
Classifier: License :: OSI Approved :: MIT License
Classifier: Operating System :: OS Independent
Classifier: Programming Language :: Python :: 3
Classifier: Programming Language :: Python :: 3.8
Classifier: Programming Language :: Python :: 3.9
Classifier: Programming Language :: Python :: 3.10
Classifier: Programming Language :: Python :: 3.11
Classifier: Programming Language :: Python :: 3.12
Classifier: Programming Language :: Python :: 3.13
Classifier: Programming Language :: Python :: 3.14
Classifier: Topic :: Scientific/Engineering :: Bio-Informatics
Requires-Python: >=3.8
Requires-Dist: numpy
Requires-Dist: pandas
Provides-Extra: dev
Requires-Dist: mypy>=1.0; extra == 'dev'
Requires-Dist: pylint>=2.0; extra == 'dev'
Requires-Dist: pytest>=7.0; extra == 'dev'
